pip_fluigio/__fluig_services_base/__init__.py
pip_fluigio/__fluig_services_base/card.py
pip_fluigio/__fluig_services_base/colleague_group.py
pip_fluigio/__fluig_services_base/dataset.py
pip_fluigio/__fluig_services_base/document.py
pip_fluigio/__fluig_services_base/factories.py
pip_fluigio/__fluig_services_base/interfaces/__init__.py
pip_fluigio/__fluig_services_base/interfaces/card.py
pip_fluigio/__fluig_services_base/interfaces/dataset.py
pip_fluigio/__fluig_services_base/interfaces/workflow_engine.py
pip_fluigio/__fluig_services_base/token.py
pip_fluigio/__fluig_services_base/workflow_engine.py
pip_fluigio/__init__.py
pip_fluigio/adapters/__init__.py
pip_fluigio/adapters/card.py
pip_fluigio/adapters/dataset.py
pip_fluigio/adapters/workflow_engine.py
pip_fluigio/fluig_services/__init__.py
pip_fluigio/fluig_services/card.py
pip_fluigio/fluig_services/colleague_group.py
pip_fluigio/fluig_services/dataset.py
pip_fluigio/fluig_services/document.py
pip_fluigio/fluig_services/infraestruture/__init__.py
pip_fluigio/fluig_services/infraestruture/server.py
pip_fluigio/fluig_services/token.py
pip_fluigio/fluig_services/workflow_engine.py
pip_fluigio/tests/__init__.py
pip_fluigio/tests/adapters/__init__.py
pip_fluigio/utils/__init__.py
pip_fluigio/utils/commomns.py
pip_fluigio/utils/exceptions.py
pip_fluigio/utils/logger.py
pip_fluigio-0.2.6.dist-info/METADATA
pip_fluigio-0.2.6.dist-info/WHEEL
pip_fluigio-0.2.6.dist-info/RECORD
