Metadata-Version: 2.1
Name: pip-fluigio
Version: 0.2.6
Summary: abstratct library  services soap plataform fluig
Author: Rodrigo Becker
Author-email: rodrigo.beckermore@gmail.com
Requires-Python: >=3.9,<4.0
Classifier: Programming Language :: Python :: 3
Classifier: Programming Language :: Python :: 3.9
Classifier: Programming Language :: Python :: 3.10
Classifier: Programming Language :: Python :: 3.11
Requires-Dist: loguru (>=0.6.0,<0.7.0)
Requires-Dist: pydantic (>=1.10.2,<2.0.0)
Requires-Dist: zeep (>=4.1.0,<5.0.0)
